rtl/fifo.sv
`timescale 1ns/1ps

module fifo (
    input  logic        clk,
    input  logic        rst,
    input  logic        wr_en,
    input  logic        rd_en,
    input  logic [7:0]  din,
    output logic [7:0]  dout,
    output logic        full,
    output logic        empty
);

    logic [7:0] mem [0:7];
    logic [2:0] wr_ptr;
    logic [2:0] rd_ptr;
    logic [3:0] count;

    always_ff @(posedge clk) begin
        if (rst) begin
            wr_ptr <= 3'b000;
            rd_ptr <= 3'b000;
            count  <= 4'b0000;
            dout   <= 8'b0;
        end
        else begin
            if (wr_en && !full) begin
                mem[wr_ptr] <= din;
                wr_ptr      <= wr_ptr + 1;
                count       <= count + 1;
            end
            if (rd_en && !empty) begin
                dout   <= mem[rd_ptr];
                rd_ptr <= rd_ptr + 1;
                count  <= count - 1;
            end
        end
    end

    always_comb begin
        full  = (count == 4'd8);
        empty = (count == 4'd0);
    end

endmodule

tb/fifo_tb.sv
`timescale 1ns/1ps

module fifo_tb;

    logic        clk;
    logic        rst;
    logic        wr_en;
    logic        rd_en;
    logic [7:0]  din;
    logic [7:0]  dout;
    logic        full;
    logic        empty;

    integer pass_count, fail_count;

    fifo uut (
        .clk(clk), .rst(rst),
        .wr_en(wr_en), .rd_en(rd_en),
        .din(din), .dout(dout),
        .full(full), .empty(empty)
    );

    initial clk = 0;
    always #5 clk = ~clk;

    initial begin
        $dumpfile("sim/waveform.vcd");
        $dumpvars(0, fifo_tb);
    end

    task write_fifo(input [7:0] data);
        @(negedge clk);
        wr_en = 1;
        din   = data;
        @(posedge clk);
        #1;
        wr_en = 0;
    endtask

    task read_check(input [7:0] expected);
        @(negedge clk);
        rd_en = 1;
        @(posedge clk);
        #1;
        if(dout == expected) begin
            $display("PASS: Read = %h (expected %h)", dout, expected);
            pass_count = pass_count + 1;
        end else begin
            $display("FAIL: Expected %h got %h", expected, dout);
            fail_count = fail_count + 1;
        end
        rd_en = 0;
    endtask

    initial begin
        pass_count = 0;
        fail_count = 0;

        rst   = 1;
        wr_en = 0;
        rd_en = 0;
        din   = 0;

        repeat(3) @(posedge clk);
        @(negedge clk);
        rst = 0;

        // write 4 values
        write_fifo(8'hAA);
        write_fifo(8'hBB);
        write_fifo(8'hCC);
        write_fifo(8'hDD);

        @(posedge clk);

        // read AA BB CC DD
        read_check(8'hAA);
        read_check(8'hBB);
        read_check(8'hCC);
        read_check(8'hDD);

        $display("==============================");
        $display("PASSED: %0d / %0d", pass_count, pass_count+fail_count);
        $display("FAILED: %0d / %0d", fail_count, pass_count+fail_count);
        $display("==============================");
        $finish;
    end

endmodule

sim/waveform.vcd
$version Generated by VerilatedVcd $end
$timescale 1ps $end
 $scope module $rootio $end
 $upscope $end
 $scope module fifo_tb $end
  $var wire 1 7 clk $end
  $var wire 1 # rst $end
  $var wire 1 $ wr_en $end
  $var wire 1 % rd_en $end
  $var wire 8 & din [7:0] $end
  $var wire 8 ) dout [7:0] $end
  $var wire 1 * full $end
  $var wire 1 + empty $end
  $var wire 32 ' pass_count [31:0] $end
  $var wire 32 ( fail_count [31:0] $end
  $scope module uut $end
   $var wire 1 7 clk $end
   $var wire 1 # rst $end
   $var wire 1 $ wr_en $end
   $var wire 1 % rd_en $end
   $var wire 8 & din [7:0] $end
   $var wire 8 ) dout [7:0] $end
   $var wire 1 * full $end
   $var wire 1 + empty $end
   $var wire 8 , mem[0] [7:0] $end
   $var wire 8 - mem[1] [7:0] $end
   $var wire 8 . mem[2] [7:0] $end
   $var wire 8 / mem[3] [7:0] $end
   $var wire 8 0 mem[4] [7:0] $end
   $var wire 8 1 mem[5] [7:0] $end
   $var wire 8 2 mem[6] [7:0] $end
   $var wire 8 3 mem[7] [7:0] $end
   $var wire 3 4 wr_ptr [2:0] $end
   $var wire 3 5 rd_ptr [2:0] $end
   $var wire 4 6 count [3:0] $end
  $upscope $end
 $upscope $end
$enddefinitions $end


#0
1#
0$
0%
b00000000 &
b00000000000000000000000000000000 '
b00000000000000000000000000000000 (
b00000000 )
0*
1+
b00000000 ,
b00000000 -
b00000000 .
b00000000 /
b00000000 0
b00000000 1
b00000000 2
b00000000 3
b000 4
b000 5
b0000 6
07
#5000
17
#10000
07
#15000
17
#20000
07
#25000
17
#30000
0#
07
#35000
17
#40000
1$
b10101010 &
07
#45000
0+
b10101010 ,
b001 4
b0001 6
17
#46000
0$
#50000
1$
b10111011 &
07
#55000
b10111011 -
b010 4
b0010 6
17
#56000
0$
#60000
1$
b11001100 &
07
#65000
b11001100 .
b011 4
b0011 6
17
#66000
0$
#70000
1$
b11011101 &
07
#75000
b11011101 /
b100 4
b0100 6
17
#76000
0$
#80000
07
#85000
17
#90000
1%
07
#95000
b10101010 )
b001 5
b0011 6
17
#96000
0%
b00000000000000000000000000000001 '
#100000
1%
07
#105000
b10111011 )
b010 5
b0010 6
17
#106000
0%
b00000000000000000000000000000010 '
#110000
1%
07
#115000
b11001100 )
b011 5
b0001 6
17
#116000
0%
b00000000000000000000000000000011 '
#120000
1%
07
#125000
b11011101 )
1+
b100 5
b0000 6
17
#126000
0%
b00000000000000000000000000000100 '
