rtl/fifo.sv
`timescale 1ns/1ps

module fifo (
    input  logic        clk,
    input  logic        rst,
    input  logic        wr_en,
    input  logic        rd_en,
    input  logic [7:0]  din,
    output logic [7:0]  dout,
    output logic        full,
    output logic        empty
);

    logic [7:0] mem [0:7];
    logic [2:0] wr_ptr;
    logic [2:0] rd_ptr;
    logic [3:0] count;

    always_ff @(posedge clk) begin
        if (rst) begin
            wr_ptr <= 3'b000;
            rd_ptr <= 3'b000;
            count  <= 4'b0000;
            dout   <= 8'b0;
        end
        else begin
            if (wr_en && !full) begin
                mem[wr_ptr] <= din;
                wr_ptr      <= wr_ptr + 1;
                count       <= count + 1;
            end
            if (rd_en && !empty) begin
                dout   <= mem[rd_ptr];
                rd_ptr <= rd_ptr + 1;
                count  <= count - 1;
            end
        end
    end

    always_comb begin
        full  = (count == 4'd8);
        empty = (count == 4'd0);
    end

endmodule

tb/fifo_tb.sv
`timescale 1ns/1ps

module fifo_tb;

    logic        clk;
    logic        rst;
    logic        wr_en;
    logic        rd_en;
    logic [7:0]  din;
    logic [7:0]  dout;
    logic        full;
    logic        empty;

    integer pass_count, fail_count;
    integer rand_pass,  rand_fail;
    integer sw_head, sw_tail, sw_count;
    integer num_ops, i, op;
    reg [7:0] sw_queue [0:7];
    reg [7:0] rand_data;

    fifo uut (
        .clk(clk), .rst(rst),
        .wr_en(wr_en), .rd_en(rd_en),
        .din(din), .dout(dout),
        .full(full), .empty(empty)
    );

    initial clk = 0;
    always #5 clk = ~clk;

    initial begin
        $dumpfile("sim/waveform.vcd");
        $dumpvars(0, fifo_tb);
    end

    task write_fifo(input [7:0] data);
        @(negedge clk);
        wr_en = 1;
        din   = data;
        @(posedge clk);
        #1;
        wr_en = 0;
    endtask

    task write_only(input [7:0] data);
        @(negedge clk);
        wr_en = 1;
        din   = data;
        @(posedge clk);
        #1;
    endtask

    task read_check(input [7:0] expected);
        @(negedge clk);
        rd_en = 1;
        @(posedge clk);
        #1;
        if(dout == expected) begin
            $display("PASS: Read = %h (expected %h)", dout, expected);
            pass_count = pass_count + 1;
        end else begin
            $display("FAIL: Expected %h got %h", expected, dout);
            fail_count = fail_count + 1;
        end
        rd_en = 0;
    endtask

    initial begin
        pass_count = 0;
        fail_count = 0;

        rst   = 1;
        wr_en = 0;
        rd_en = 0;
        din   = 0;

        repeat(3) @(posedge clk);
        @(negedge clk);
        rst = 0;

        // ── Basic Order Test ─────────────────────
        $display("\n--- Basic Order Test ---");
        write_fifo(8'hAA);
        write_fifo(8'hBB);
        write_fifo(8'hCC);
        write_fifo(8'hDD);
        @(posedge clk);
        read_check(8'hAA);
        read_check(8'hBB);
        read_check(8'hCC);
        read_check(8'hDD);

        // ── Full Flag Test ───────────────────────
        $display("\n--- Full Flag Test ---");
        repeat(8) begin
            write_only(8'hFF);
        end
        wr_en = 0;
        @(posedge clk);
        #1;
        if(full == 1) begin
            $display("PASS: Full flag set correctly");
            pass_count = pass_count + 1;
        end else begin
            $display("FAIL: Full flag not set");
            fail_count = fail_count + 1;
        end

        // ── Empty Flag Test ──────────────────────
        $display("\n--- Empty Flag Test ---");
        repeat(8) begin
            read_check(8'hFF);
        end
        @(posedge clk);
        #1;
        if(empty == 1) begin
            $display("PASS: Empty flag set correctly");
            pass_count = pass_count + 1;
        end else begin
            $display("FAIL: Empty flag not set");
            fail_count = fail_count + 1;
        end

        $display("\n==============================");
        $display(" DIRECTED TESTS");
        $display(" PASSED: %0d / %0d", pass_count, pass_count+fail_count);
        $display(" FAILED: %0d / %0d", fail_count, pass_count+fail_count);
        $display("==============================");

        // ── Random Verification ──────────────────
        $display("\n--- Random Verification (200 ops) ---");
        rand_pass = 0;
        rand_fail = 0;
        sw_head   = 0;
        sw_tail   = 0;
        sw_count  = 0;

        // reset FIFO before random test
        @(negedge clk);
        rst = 1;
        @(posedge clk);
        #1;
        rst = 0;

        num_ops = 200;

        for(i = 0; i < num_ops; i = i + 1) begin
            op = $random % 2;

            if(op == 0 && sw_count < 8) begin
                /* verilator lint_off WIDTHTRUNC */
rand_data = $random;
/* verilator lint_on WIDTHTRUNC */
                sw_queue[sw_tail] = rand_data;
                sw_tail   = (sw_tail + 1) % 8;
                sw_count  = sw_count + 1;
                write_only(rand_data);
                wr_en = 0;

            end else if(op == 1 && sw_count > 0) begin
                @(negedge clk);
                rd_en = 1;
                @(posedge clk);
                #1;
                if(dout == sw_queue[sw_head]) begin
                    rand_pass = rand_pass + 1;
                end else begin
                    $display("FAIL: op%0d expected %h got %h", i, sw_queue[sw_head], dout);
                    rand_fail = rand_fail + 1;
                end
                rd_en    = 0;
                sw_head  = (sw_head + 1) % 8;
                sw_count = sw_count - 1;
            end
        end

        $display("\n==============================");
        $display(" RANDOM TESTS (200 ops)");
        $display(" PASSED: %0d", rand_pass);
        $display(" FAILED: %0d", rand_fail);
        $display("==============================");
        $finish;
    end

endmodule

sim/waveform.vcd
$version Generated by VerilatedVcd $end
$timescale 1ps $end
 $scope module $rootio $end
 $upscope $end
 $scope module fifo_tb $end
  $var wire 1 H clk $end
  $var wire 1 # rst $end
  $var wire 1 $ wr_en $end
  $var wire 1 % rd_en $end
  $var wire 8 & din [7:0] $end
  $var wire 8 : dout [7:0] $end
  $var wire 1 ; full $end
  $var wire 1 < empty $end
  $var wire 32 ' pass_count [31:0] $end
  $var wire 32 ( fail_count [31:0] $end
  $var wire 32 ) rand_pass [31:0] $end
  $var wire 32 * rand_fail [31:0] $end
  $var wire 32 + sw_head [31:0] $end
  $var wire 32 , sw_tail [31:0] $end
  $var wire 32 - sw_count [31:0] $end
  $var wire 32 . num_ops [31:0] $end
  $var wire 32 / i [31:0] $end
  $var wire 32 0 op [31:0] $end
  $var wire 8 1 sw_queue[0] [7:0] $end
  $var wire 8 2 sw_queue[1] [7:0] $end
  $var wire 8 3 sw_queue[2] [7:0] $end
  $var wire 8 4 sw_queue[3] [7:0] $end
  $var wire 8 5 sw_queue[4] [7:0] $end
  $var wire 8 6 sw_queue[5] [7:0] $end
  $var wire 8 7 sw_queue[6] [7:0] $end
  $var wire 8 8 sw_queue[7] [7:0] $end
  $var wire 8 9 rand_data [7:0] $end
  $scope module uut $end
   $var wire 1 H clk $end
   $var wire 1 # rst $end
   $var wire 1 $ wr_en $end
   $var wire 1 % rd_en $end
   $var wire 8 & din [7:0] $end
   $var wire 8 : dout [7:0] $end
   $var wire 1 ; full $end
   $var wire 1 < empty $end
   $var wire 8 = mem[0] [7:0] $end
   $var wire 8 > mem[1] [7:0] $end
   $var wire 8 ? mem[2] [7:0] $end
   $var wire 8 @ mem[3] [7:0] $end
   $var wire 8 A mem[4] [7:0] $end
   $var wire 8 B mem[5] [7:0] $end
   $var wire 8 C mem[6] [7:0] $end
   $var wire 8 D mem[7] [7:0] $end
   $var wire 3 E wr_ptr [2:0] $end
   $var wire 3 F rd_ptr [2:0] $end
   $var wire 4 G count [3:0] $end
  $upscope $end
 $upscope $end
$enddefinitions $end


#0
1#
0$
0%
b00000000 &
b00000000000000000000000000000000 '
b00000000000000000000000000000000 (
b00000000000000000000000000000000 )
b00000000000000000000000000000000 *
b00000000000000000000000000000000 +
b00000000000000000000000000000000 ,
b00000000000000000000000000000000 -
b00000000000000000000000000000000 .
b00000000000000000000000000000000 /
b00000000000000000000000000000000 0
b00000000 1
b00000000 2
b00000000 3
b00000000 4
b00000000 5
b00000000 6
b00000000 7
b00000000 8
b00000000 9
b00000000 :
0;
1<
b00000000 =
b00000000 >
b00000000 ?
b00000000 @
b00000000 A
b00000000 B
b00000000 C
b00000000 D
b000 E
b000 F
b0000 G
0H
#5000
1H
#10000
0H
#15000
1H
#20000
0H
#25000
1H
#30000
0#
0H
#35000
1H
#40000
1$
b10101010 &
0H
#45000
0<
b10101010 =
b001 E
b0001 G
1H
#46000
0$
#50000
1$
b10111011 &
0H
#55000
b10111011 >
b010 E
b0010 G
1H
#56000
0$
#60000
1$
b11001100 &
0H
#65000
b11001100 ?
b011 E
b0011 G
1H
#66000
0$
#70000
1$
b11011101 &
0H
#75000
b11011101 @
b100 E
b0100 G
1H
#76000
0$
#80000
0H
#85000
1H
#90000
1%
0H
#95000
b10101010 :
b001 F
b0011 G
1H
#96000
0%
b00000000000000000000000000000001 '
#100000
1%
0H
#105000
b10111011 :
b010 F
b0010 G
1H
#106000
0%
b00000000000000000000000000000010 '
#110000
1%
0H
#115000
b11001100 :
b011 F
b0001 G
1H
#116000
0%
b00000000000000000000000000000011 '
#120000
1%
0H
#125000
b11011101 :
1<
b100 F
b0000 G
1H
#126000
0%
b00000000000000000000000000000100 '
#130000
1$
b11111111 &
0H
#135000
0<
b11111111 A
b101 E
b0001 G
1H
#136000
#140000
0H
#145000
b11111111 B
b110 E
b0010 G
1H
#146000
#150000
0H
#155000
b11111111 C
b111 E
b0011 G
1H
#156000
#160000
0H
#165000
b11111111 D
b000 E
b0100 G
1H
#166000
#170000
0H
#175000
b11111111 =
b001 E
b0101 G
1H
#176000
#180000
0H
#185000
b11111111 >
b010 E
b0110 G
1H
#186000
#190000
0H
#195000
b11111111 ?
b011 E
b0111 G
1H
#196000
#200000
0H
#205000
1;
b11111111 @
b100 E
b1000 G
1H
#206000
0$
#210000
0H
#215000
1H
#216000
b00000000000000000000000000000101 '
#220000
1%
0H
#225000
b11111111 :
0;
b101 F
b0111 G
1H
#226000
0%
b00000000000000000000000000000110 '
#230000
1%
0H
#235000
b110 F
b0110 G
1H
#236000
0%
b00000000000000000000000000000111 '
#240000
1%
0H
#245000
b111 F
b0101 G
1H
#246000
0%
b00000000000000000000000000001000 '
#250000
1%
0H
#255000
b000 F
b0100 G
1H
#256000
0%
b00000000000000000000000000001001 '
#260000
1%
0H
#265000
b001 F
b0011 G
1H
#266000
0%
b00000000000000000000000000001010 '
#270000
1%
0H
#275000
b010 F
b0010 G
1H
#276000
0%
b00000000000000000000000000001011 '
#280000
1%
0H
#285000
b011 F
b0001 G
1H
#286000
0%
b00000000000000000000000000001100 '
#290000
1%
0H
#295000
1<
b100 F
b0000 G
1H
#296000
0%
b00000000000000000000000000001101 '
#300000
0H
#305000
1H
#306000
b00000000000000000000000000001110 '
#310000
1#
0H
#315000
b00000000 :
b000 E
b000 F
1H
#316000
0#
b00000000000000000000000000000001 ,
b00000000000000000000000000000001 -
b00000000000000000000000011001000 .
b10011100 1
b10011100 9
#320000
1$
b10011100 &
0H
#325000
0<
b10011100 =
b001 E
b0001 G
1H
#326000
0$
b00000000000000000000000000000010 ,
b00000000000000000000000000000010 -
b00000000000000000000000000000001 /
b11100100 2
b11100100 9
#330000
1$
b11100100 &
0H
#335000
b11100100 >
b010 E
b0010 G
1H
#336000
0$
b00000000000000000000000000000011 ,
b00000000000000000000000000000011 -
b00000000000000000000000000000010 /
b10111100 3
b10111100 9
#340000
1$
b10111100 &
0H
#345000
b10111100 ?
b011 E
b0011 G
1H
#346000
0$
b00000000000000000000000000000100 ,
b00000000000000000000000000000100 -
b00000000000000000000000000000011 /
b11100100 4
b11100100 9
#350000
1$
b11100100 &
0H
#355000
b11100100 @
b100 E
b0100 G
1H
#356000
0$
b00000000000000000000000000000100 /
b00000000000000000000000000000001 0
#360000
1%
0H
#365000
b10011100 :
b001 F
b0011 G
1H
#366000
0%
b00000000000000000000000000000001 )
b00000000000000000000000000000001 +
b00000000000000000000000000000011 -
b00000000000000000000000000000110 /
#370000
1%
0H
#375000
b11100100 :
b010 F
b0010 G
1H
#376000
0%
b00000000000000000000000000000010 )
b00000000000000000000000000000010 +
b00000000000000000000000000000101 ,
b00000000000000000000000000001001 /
b00000000000000000000000000000000 0
b01100010 5
b01100010 9
#380000
1$
b01100010 &
0H
#385000
b01100010 A
b101 E
b0011 G
1H
#386000
0$
b00000000000000000000000000001010 /
b00000000000000000000000000000001 0
#390000
1%
0H
#395000
b10111100 :
b011 F
b0010 G
1H
#396000
0%
b00000000000000000000000000000011 )
b00000000000000000000000000000011 +
b00000000000000000000000000000110 ,
b00000000000000000000000000001011 /
b00000000000000000000000000000000 0
b01010110 6
b01010110 9
#400000
1$
b01010110 &
0H
#405000
b01010110 B
b110 E
b0011 G
1H
#406000
0$
b00000000000000000000000000000111 ,
b00000000000000000000000000000100 -
b00000000000000000000000000001101 /
b00111011 7
b00111011 9
#410000
1$
b00111011 &
0H
#415000
b00111011 C
b111 E
b0100 G
1H
#416000
0$
b00000000000000000000000000000000 ,
b00000000000000000000000000000101 -
b00000000000000000000000000001110 /
b10110010 8
b10110010 9
#420000
1$
b10110010 &
0H
#425000
b10110010 D
b000 E
b0101 G
1H
#426000
0$
b00000000000000000000000000000001 ,
b00000000000000000000000000000110 -
b00000000000000000000000000001111 /
b00011110 1
b00011110 9
#430000
1$
b00011110 &
0H
#435000
b00011110 =
b001 E
b0110 G
1H
#436000
0$
b00000000000000000000000000000010 ,
b00000000000000000000000000000111 -
b00000000000000000000000000010000 /
b10011110 2
b10011110 9
#440000
1$
b10011110 &
0H
#445000
b10011110 >
b010 E
b0111 G
1H
#446000
0$
b00000000000000000000000000000011 ,
b00000000000000000000000000001000 -
b00000000000000000000000000010001 /
b00010000 3
b00010000 9
#450000
1$
b00010000 &
0H
#455000
1;
b00010000 ?
b011 E
b1000 G
1H
#456000
0$
b00000000000000000000000000010011 /
b00000000000000000000000000000001 0
#460000
1%
0H
#465000
b11100100 :
0;
b100 F
b0111 G
1H
#466000
0%
b00000000000000000000000000000100 )
b00000000000000000000000000000100 +
b00000000000000000000000000000100 ,
b00000000000000000000000000010100 /
b00000000000000000000000000000000 0
b00011101 4
b00011101 9
#470000
1$
b00011101 &
0H
#475000
1;
b00011101 @
b100 E
b1000 G
1H
#476000
0$
b00000000000000000000000000011000 /
b00000000000000000000000000000001 0
#480000
1%
0H
#485000
b01100010 :
0;
b101 F
b0111 G
1H
#486000
0%
b00000000000000000000000000000101 )
b00000000000000000000000000000101 +
b00000000000000000000000000000101 ,
b00000000000000000000000000011001 /
b00000000000000000000000000000000 0
b01101111 5
b01101111 9
#490000
1$
b01101111 &
0H
#495000
1;
b01101111 A
b101 E
b1000 G
1H
#496000
0$
b00000000000000000000000000100010 /
b00000000000000000000000000000001 0
#500000
1%
0H
#505000
b01010110 :
0;
b110 F
b0111 G
1H
#506000
0%
b00000000000000000000000000000110 )
b00000000000000000000000000000110 +
b00000000000000000000000000000110 ,
b00000000000000000000000000100011 /
b00000000000000000000000000000000 0
b11100010 6
b11100010 9
#510000
1$
b11100010 &
0H
#515000
1;
b11100010 B
b110 E
b1000 G
1H
#516000
0$
b00000000000000000000000000101000 /
b00000000000000000000000000000001 0
#520000
1%
0H
#525000
b00111011 :
0;
b111 F
b0111 G
1H
#526000
0%
b00000000000000000000000000000111 )
b00000000000000000000000000000111 +
b00000000000000000000000000000111 ,
b00000000000000000000000000101001 /
b00000000000000000000000000000000 0
b11000101 7
b11000101 9
#530000
1$
b11000101 &
0H
#535000
1;
b11000101 C
b111 E
b1000 G
1H
#536000
0$
b00000000000000000000000000101010 /
b00000000000000000000000000000001 0
#540000
1%
0H
#545000
b10110010 :
0;
b000 F
b0111 G
1H
#546000
0%
b00000000000000000000000000001000 )
b00000000000000000000000000000000 +
b00000000000000000000000000000000 ,
b00000000000000000000000000101100 /
b00000000000000000000000000000000 0
b11110011 8
b11110011 9
#550000
1$
b11110011 &
0H
#555000
1;
b11110011 D
b000 E
b1000 G
1H
#556000
0$
b00000000000000000000000000110000 /
b00000000000000000000000000000001 0
#560000
1%
0H
#565000
b00011110 :
0;
b001 F
b0111 G
1H
#566000
0%
b00000000000000000000000000001001 )
b00000000000000000000000000000001 +
b00000000000000000000000000000001 ,
b00000000000000000000000000110010 /
b00000000000000000000000000000000 0
b11101111 1
b11101111 9
#570000
1$
b11101111 &
0H
#575000
1;
b11101111 =
b001 E
b1000 G
1H
#576000
0$
b00000000000000000000000000110011 /
b00000000000000000000000000000001 0
#580000
1%
0H
#585000
b10011110 :
0;
b010 F
b0111 G
1H
#586000
0%
b00000000000000000000000000001010 )
b00000000000000000000000000000010 +
b00000000000000000000000000000111 -
b00000000000000000000000000110101 /
#590000
1%
0H
#595000
b00010000 :
b011 F
b0110 G
1H
#596000
0%
b00000000000000000000000000001011 )
b00000000000000000000000000000011 +
b00000000000000000000000000000010 ,
b00000000000000000000000000110110 /
b00000000000000000000000000000000 0
b11101010 2
b11101010 9
#600000
1$
b11101010 &
0H
#605000
b11101010 >
b010 E
b0111 G
1H
#606000
0$
b00000000000000000000000000000011 ,
b00000000000000000000000000001000 -
b00000000000000000000000000110111 /
b01010100 3
b01010100 9
#610000
1$
b01010100 &
0H
#615000
1;
b01010100 ?
b011 E
b1000 G
1H
#616000
0$
b00000000000000000000000000111001 /
b00000000000000000000000000000001 0
#620000
1%
0H
#625000
b00011101 :
0;
b100 F
b0111 G
1H
#626000
0%
b00000000000000000000000000001100 )
b00000000000000000000000000000100 +
b00000000000000000000000000000111 -
b00000000000000000000000000111011 /
#630000
1%
0H
#635000
b01101111 :
b101 F
b0110 G
1H
#636000
0%
b00000000000000000000000000001101 )
b00000000000000000000000000000101 +
b00000000000000000000000000000110 -
b00000000000000000000000000111100 /
#640000
1%
0H
#645000
b11100010 :
b110 F
b0101 G
1H
#646000
0%
b00000000000000000000000000001110 )
b00000000000000000000000000000110 +
b00000000000000000000000000000101 -
b00000000000000000000000000111101 /
#650000
1%
0H
#655000
b11000101 :
b111 F
b0100 G
1H
#656000
0%
b00000000000000000000000000001111 )
b00000000000000000000000000000111 +
b00000000000000000000000000000100 ,
b00000000000000000000000000111110 /
b00000000000000000000000000000000 0
b11001111 4
b11001111 9
#660000
1$
b11001111 &
0H
#665000
b11001111 @
b100 E
b0101 G
1H
#666000
0$
b00000000000000000000000000111111 /
b00000000000000000000000000000001 0
#670000
1%
0H
#675000
b11110011 :
b000 F
b0100 G
1H
#676000
0%
b00000000000000000000000000010000 )
b00000000000000000000000000000000 +
b00000000000000000000000000000100 -
b00000000000000000000000001000000 /
#680000
1%
0H
#685000
b11101111 :
b001 F
b0011 G
1H
#686000
0%
b00000000000000000000000000010001 )
b00000000000000000000000000000001 +
b00000000000000000000000000000011 -
b00000000000000000000000001000001 /
#690000
1%
0H
#695000
b11101010 :
b010 F
b0010 G
1H
#696000
0%
b00000000000000000000000000010010 )
b00000000000000000000000000000010 +
b00000000000000000000000000000101 ,
b00000000000000000000000001000010 /
b00000000000000000000000000000000 0
b10101111 5
b10101111 9
#700000
1$
b10101111 &
0H
#705000
b10101111 A
b101 E
b0011 G
1H
#706000
0$
b00000000000000000000000001000100 /
b00000000000000000000000000000001 0
#710000
1%
0H
#715000
b01010100 :
b011 F
b0010 G
1H
#716000
0%
b00000000000000000000000000010011 )
b00000000000000000000000000000011 +
b00000000000000000000000000000110 ,
b00000000000000000000000001000111 /
b00000000000000000000000000000000 0
b01110111 6
b01110111 9
#720000
1$
b01110111 &
0H
#725000
b01110111 B
b110 E
b0011 G
1H
#726000
0$
b00000000000000000000000000000111 ,
b00000000000000000000000000000100 -
b00000000000000000000000001001000 /
b00001011 7
b00001011 9
#730000
1$
b00001011 &
0H
#735000
b00001011 C
b111 E
b0100 G
1H
#736000
0$
b00000000000000000000000001001001 /
b00000000000000000000000000000001 0
#740000
1%
0H
#745000
b11001111 :
b100 F
b0011 G
1H
#746000
0%
b00000000000000000000000000010100 )
b00000000000000000000000000000100 +
b00000000000000000000000000000011 -
b00000000000000000000000001001010 /
#750000
1%
0H
#755000
b10101111 :
b101 F
b0010 G
1H
#756000
0%
b00000000000000000000000000010101 )
b00000000000000000000000000000101 +
b00000000000000000000000000000000 ,
b00000000000000000000000001001011 /
b00000000000000000000000000000000 0
b00000010 8
b00000010 9
#760000
1$
b00000010 &
0H
#765000
b00000010 D
b000 E
b0011 G
1H
#766000
0$
b00000000000000000000000000000001 ,
b00000000000000000000000000000100 -
b00000000000000000000000001001101 /
b11000010 1
b11000010 9
#770000
1$
b11000010 &
0H
#775000
b11000010 =
b001 E
b0100 G
1H
#776000
0$
b00000000000000000000000001001110 /
b00000000000000000000000000000001 0
#780000
1%
0H
#785000
b01110111 :
b110 F
b0011 G
1H
#786000
0%
b00000000000000000000000000010110 )
b00000000000000000000000000000110 +
b00000000000000000000000000000010 ,
b00000000000000000000000001001111 /
b00000000000000000000000000000000 0
b01100100 2
b01100100 9
#790000
1$
b01100100 &
0H
#795000
b01100100 >
b010 E
b0100 G
1H
#796000
0$
b00000000000000000000000001010000 /
b00000000000000000000000000000001 0
#800000
1%
0H
#805000
b00001011 :
b111 F
b0011 G
1H
#806000
0%
b00000000000000000000000000010111 )
b00000000000000000000000000000111 +
b00000000000000000000000000000011 -
b00000000000000000000000001010010 /
#810000
1%
0H
#815000
b00000010 :
b000 F
b0010 G
1H
#816000
0%
b00000000000000000000000000011000 )
b00000000000000000000000000000000 +
b00000000000000000000000000000010 -
b00000000000000000000000001010100 /
#820000
1%
0H
#825000
b11000010 :
b001 F
b0001 G
1H
#826000
0%
b00000000000000000000000000011001 )
b00000000000000000000000000000001 +
b00000000000000000000000000000001 -
b00000000000000000000000001010101 /
#830000
1%
0H
#835000
b01100100 :
1<
b010 F
b0000 G
1H
#836000
0%
b00000000000000000000000000011010 )
b00000000000000000000000000000010 +
b00000000000000000000000000000011 ,
b00000000000000000000000001010111 /
b00000000000000000000000000000000 0
b01100010 3
b01100010 9
#840000
1$
b01100010 &
0H
#845000
0<
b01100010 ?
b011 E
b0001 G
1H
#846000
0$
b00000000000000000000000000000100 ,
b00000000000000000000000000000010 -
b00000000000000000000000001011000 /
b10010000 4
b10010000 9
#850000
1$
b10010000 &
0H
#855000
b10010000 @
b100 E
b0010 G
1H
#856000
0$
b00000000000000000000000001011001 /
b00000000000000000000000000000001 0
#860000
1%
0H
#865000
b01100010 :
b011 F
b0001 G
1H
#866000
0%
b00000000000000000000000000011011 )
b00000000000000000000000000000011 +
b00000000000000000000000000000101 ,
b00000000000000000000000001011010 /
b00000000000000000000000000000000 0
b00010000 5
b00010000 9
#870000
1$
b00010000 &
0H
#875000
b00010000 A
b101 E
b0010 G
1H
#876000
0$
b00000000000000000000000000000110 ,
b00000000000000000000000000000011 -
b00000000000000000000000001011011 /
b01110011 6
b01110011 9
#880000
1$
b01110011 &
0H
#885000
b01110011 B
b110 E
b0011 G
1H
#886000
0$
b00000000000000000000000000000111 ,
b00000000000000000000000000000100 -
b00000000000000000000000001011100 /
b00111101 7
b00111101 9
#890000
1$
b00111101 &
0H
#895000
b00111101 C
b111 E
b0100 G
1H
#896000
0$
b00000000000000000000000000000000 ,
b00000000000000000000000000000101 -
b00000000000000000000000001011101 /
b00001110 8
b00001110 9
#900000
1$
b00001110 &
0H
#905000
b00001110 D
b000 E
b0101 G
1H
#906000
0$
b00000000000000000000000001011110 /
b00000000000000000000000000000001 0
#910000
1%
0H
#915000
b10010000 :
b100 F
b0100 G
1H
#916000
0%
b00000000000000000000000000011100 )
b00000000000000000000000000000100 +
b00000000000000000000000000000100 -
b00000000000000000000000001011111 /
#920000
1%
0H
#925000
b00010000 :
b101 F
b0011 G
1H
#926000
0%
b00000000000000000000000000011101 )
b00000000000000000000000000000101 +
b00000000000000000000000000000011 -
b00000000000000000000000001100000 /
#930000
1%
0H
#935000
b01110011 :
b110 F
b0010 G
1H
#936000
0%
b00000000000000000000000000011110 )
b00000000000000000000000000000110 +
b00000000000000000000000000000001 ,
b00000000000000000000000001100001 /
b00000000000000000000000000000000 0
b00110011 1
b00110011 9
#940000
1$
b00110011 &
0H
#945000
b00110011 =
b001 E
b0011 G
1H
#946000
0$
b00000000000000000000000000000010 ,
b00000000000000000000000000000100 -
b00000000000000000000000001100010 /
b10110110 2
b10110110 9
#950000
1$
b10110110 &
0H
#955000
b10110110 >
b010 E
b0100 G
1H
#956000
0$
b00000000000000000000000000000011 ,
b00000000000000000000000000000101 -
b00000000000000000000000001100100 /
b01100111 3
b01100111 9
#960000
1$
b01100111 &
0H
#965000
b01100111 ?
b011 E
b0101 G
1H
#966000
0$
b00000000000000000000000001100101 /
b00000000000000000000000000000001 0
#970000
1%
0H
#975000
b00111101 :
b111 F
b0100 G
1H
#976000
0%
b00000000000000000000000000011111 )
b00000000000000000000000000000111 +
b00000000000000000000000000000100 ,
b00000000000000000000000001100110 /
b00000000000000000000000000000000 0
b11110100 4
b11110100 9
#980000
1$
b11110100 &
0H
#985000
b11110100 @
b100 E
b0101 G
1H
#986000
0$
b00000000000000000000000000000101 ,
b00000000000000000000000000000110 -
b00000000000000000000000001100111 /
b00101000 5
b00101000 9
#990000
1$
b00101000 &
0H
#995000
b00101000 A
b101 E
b0110 G
1H
#996000
0$
b00000000000000000000000000000110 ,
b00000000000000000000000000000111 -
b00000000000000000000000001101010 /
b01100100 6
b01100100 9
#1000000
1$
b01100100 &
0H
#1005000
b01100100 B
b110 E
b0111 G
1H
#1006000
0$
b00000000000000000000000000000111 ,
b00000000000000000000000000001000 -
b00000000000000000000000001101100 /
b00111101 9
#1010000
1$
b00111101 &
0H
#1015000
1;
b111 E
b1000 G
1H
#1016000
0$
b00000000000000000000000001101101 /
b00000000000000000000000000000001 0
#1020000
1%
0H
#1025000
b00001110 :
0;
b000 F
b0111 G
1H
#1026000
0%
b00000000000000000000000000100000 )
b00000000000000000000000000000000 +
b00000000000000000000000000000000 ,
b00000000000000000000000001101111 /
b00000000000000000000000000000000 0
b11101100 8
b11101100 9
#1030000
1$
b11101100 &
0H
#1035000
1;
b11101100 D
b000 E
b1000 G
1H
#1036000
0$
b00000000000000000000000001110010 /
b00000000000000000000000000000001 0
#1040000
1%
0H
#1045000
b00110011 :
0;
b001 F
b0111 G
1H
#1046000
0%
b00000000000000000000000000100001 )
b00000000000000000000000000000001 +
b00000000000000000000000000000001 ,
b00000000000000000000000001110011 /
b00000000000000000000000000000000 0
b11010100 1
b11010100 9
#1050000
1$
b11010100 &
0H
#1055000
1;
b11010100 =
b001 E
b1000 G
1H
#1056000
0$
b00000000000000000000000001110101 /
b00000000000000000000000000000001 0
#1060000
1%
0H
#1065000
b10110110 :
0;
b010 F
b0111 G
1H
#1066000
0%
b00000000000000000000000000100010 )
b00000000000000000000000000000010 +
b00000000000000000000000000000010 ,
b00000000000000000000000001110111 /
b00000000000000000000000000000000 0
b01110001 2
b01110001 9
#1070000
1$
b01110001 &
0H
#1075000
1;
b01110001 >
b010 E
b1000 G
1H
#1076000
0$
b00000000000000000000000001111000 /
b00000000000000000000000000000001 0
#1080000
1%
0H
#1085000
b01100111 :
0;
b011 F
b0111 G
1H
#1086000
0%
b00000000000000000000000000100011 )
b00000000000000000000000000000011 +
b00000000000000000000000000000011 ,
b00000000000000000000000001111010 /
b00000000000000000000000000000000 0
b11110000 3
b11110000 9
#1090000
1$
b11110000 &
0H
#1095000
1;
b11110000 ?
b011 E
b1000 G
1H
#1096000
0$
b00000000000000000000000001111100 /
b00000000000000000000000000000001 0
#1100000
1%
0H
#1105000
b11110100 :
0;
b100 F
b0111 G
1H
#1106000
0%
b00000000000000000000000000100100 )
b00000000000000000000000000000100 +
b00000000000000000000000000000100 ,
b00000000000000000000000001111101 /
b00000000000000000000000000000000 0
b00100011 4
b00100011 9
#1110000
1$
b00100011 &
0H
#1115000
1;
b00100011 @
b100 E
b1000 G
1H
#1116000
0$
b00000000000000000000000001111111 /
b00000000000000000000000000000001 0
#1120000
1%
0H
#1125000
b00101000 :
0;
b101 F
b0111 G
1H
#1126000
0%
b00000000000000000000000000100101 )
b00000000000000000000000000000101 +
b00000000000000000000000000000111 -
b00000000000000000000000010000000 /
#1130000
1%
0H
#1135000
b01100100 :
b110 F
b0110 G
1H
#1136000
0%
b00000000000000000000000000100110 )
b00000000000000000000000000000110 +
b00000000000000000000000000000101 ,
b00000000000000000000000010000010 /
b00000000000000000000000000000000 0
b11111100 5
b11111100 9
#1140000
1$
b11111100 &
0H
#1145000
b11111100 A
b101 E
b0111 G
1H
#1146000
0$
b00000000000000000000000000000110 ,
b00000000000000000000000000001000 -
b00000000000000000000000010000011 /
b01111011 6
b01111011 9
#1150000
1$
b01111011 &
0H
#1155000
1;
b01111011 B
b110 E
b1000 G
1H
#1156000
0$
b00000000000000000000000010000110 /
b00000000000000000000000000000001 0
#1160000
1%
0H
#1165000
b00111101 :
0;
b111 F
b0111 G
1H
#1166000
0%
b00000000000000000000000000100111 )
b00000000000000000000000000000111 +
b00000000000000000000000000000111 ,
b00000000000000000000000010000111 /
b00000000000000000000000000000000 0
b11010100 7
b11010100 9
#1170000
1$
b11010100 &
0H
#1175000
1;
b11010100 C
b111 E
b1000 G
1H
#1176000
0$
b00000000000000000000000010001011 /
b00000000000000000000000000000001 0
#1180000
1%
0H
#1185000
b11101100 :
0;
b000 F
b0111 G
1H
#1186000
0%
b00000000000000000000000000101000 )
b00000000000000000000000000000000 +
b00000000000000000000000000000111 -
b00000000000000000000000010001100 /
#1190000
1%
0H
#1195000
b11010100 :
b001 F
b0110 G
1H
#1196000
0%
b00000000000000000000000000101001 )
b00000000000000000000000000000001 +
b00000000000000000000000000000000 ,
b00000000000000000000000010001110 /
b00000000000000000000000000000000 0
b00100100 8
b00100100 9
#1200000
1$
b00100100 &
0H
#1205000
b00100100 D
b000 E
b0111 G
1H
#1206000
0$
b00000000000000000000000000000001 ,
b00000000000000000000000000001000 -
b00000000000000000000000010001111 /
b00000111 1
b00000111 9
#1210000
1$
b00000111 &
0H
#1215000
1;
b00000111 =
b001 E
b1000 G
1H
#1216000
0$
b00000000000000000000000010010010 /
b00000000000000000000000000000001 0
#1220000
1%
0H
#1225000
b01110001 :
0;
b010 F
b0111 G
1H
